LICENSE
MANIFEST.in
README.rst
davbackup.json.sample
davbackup.py
setup.py
davbackup.egg-info/PKG-INFO
davbackup.egg-info/SOURCES.txt
davbackup.egg-info/dependency_links.txt
davbackup.egg-info/entry_points.txt
davbackup.egg-info/requires.txt
davbackup.egg-info/top_level.txt